{
  "bg": 128, 
  "temp": "absolute", 
  "snoozeBG": 67, 
  "timestamp": "2016-10-07T01:26:15.660015", 
  "missing": [
    "duration", 
    "rate"
  ], 
  "reason": "Eventual BG 62<135, Snooze BG 67, temp 0 ~< req 0.16U/hr", 
  "eventualBG": 62, 
  "error": "missing required input fields", 
  "input": {
    "reason": "Eventual BG 62<135, Snooze BG 67, temp 0 ~< req 0.16U/hr", 
    "bg": 128, 
    "eventualBG": 62, 
    "temp": "absolute", 
    "snoozeBG": 67, 
    "mealAssist": "Off: Carbs: undefined Boluses: undefined ISF: 75, Target: 135 Deviation: 27 BGI: -9.75", 
    "tick": "+0"
  }, 
  "mealAssist": "Off: Carbs: undefined Boluses: undefined ISF: 75, Target: 135 Deviation: 27 BGI: -9.75", 
  "tick": "+0"
}