[
  {
    "trend_arrow": "FLAT", 
    "system_time": "2016-08-25T15:18:09", 
    "direction": "Flat", 
    "sgv": 107, 
    "display_time": "2016-08-25T08:19:05", 
    "date": 1472131145000.0, 
    "dateString": "2016-08-25T08:19:05", 
    "device": "openaps://cgm", 
    "type": "sgv", 
    "glucose": 107
  }, 
  {
    "trend_arrow": "FLAT", 
    "system_time": "2016-08-25T15:08:18", 
    "direction": "Flat", 
    "sgv": 114, 
    "display_time": "2016-08-25T08:09:14", 
    "date": 1472130554000.0, 
    "dateString": "2016-08-25T08:09:14", 
    "device": "openaps://cgm", 
    "type": "sgv", 
    "glucose": 114
  }, 
  {
    "trend_arrow": "FLAT", 
    "system_time": "2016-08-25T15:03:09", 
    "direction": "Flat", 
    "sgv": 115, 
    "display_time": "2016-08-25T08:04:04", 
    "date": 1472130244000.0, 
    "dateString": "2016-08-25T08:04:04", 
    "device": "openaps://cgm", 
    "type": "sgv", 
    "glucose": 115
  }, 
  {
    "trend_arrow": "FLAT", 
    "system_time": "2016-08-25T14:58:06", 
    "direction": "Flat", 
    "sgv": 114, 
    "display_time": "2016-08-25T07:59:02", 
    "date": 1472129942000.0, 
    "dateString": "2016-08-25T07:59:02", 
    "device": "openaps://cgm", 
    "type": "sgv", 
    "glucose": 114
  }, 
  {
    "trend_arrow": "FLAT", 
    "system_time": "2016-08-25T14:53:24", 
    "direction": "Flat", 
    "sgv": 114, 
    "display_time": "2016-08-25T07:54:20", 
    "date": 1472129660000.0, 
    "dateString": "2016-08-25T07:54:20", 
    "device": "openaps://cgm", 
    "type": "sgv", 
    "glucose": 114
  }, 
  {
    "trend_arrow": "FLAT", 
    "system_time": "2016-08-25T14:43:13", 
    "direction": "Flat", 
    "sgv": 111, 
    "display_time": "2016-08-25T07:44:09", 
    "date": 1472129049000.0, 
    "dateString": "2016-08-25T07:44:09", 
    "device": "openaps://cgm", 
    "type": "sgv", 
    "glucose": 111
  }, 
  {
    "trend_arrow": "FLAT", 
    "system_time": "2016-08-25T14:38:09", 
    "direction": "Flat", 
    "sgv": 110, 
    "display_time": "2016-08-25T07:39:05", 
    "date": 1472128745000.0, 
    "dateString": "2016-08-25T07:39:05", 
    "device": "openaps://cgm", 
    "type": "sgv", 
    "glucose": 110
  }
]