[
  {
    "trend_arrow": "FLAT", 
    "system_time": "2016-08-21T00:23:29", 
    "display_time": "2016-08-20T17:24:25", 
    "glucose": 159
  }, 
  {
    "trend_arrow": "FLAT", 
    "system_time": "2016-08-20T21:48:30", 
    "display_time": "2016-08-20T14:49:25", 
    "glucose": 192
  }, 
  {
    "trend_arrow": "45_UP", 
    "system_time": "2016-08-20T21:43:30", 
    "display_time": "2016-08-20T14:44:26", 
    "glucose": 189
  }, 
  {
    "trend_arrow": "45_UP", 
    "system_time": "2016-08-20T21:38:43", 
    "display_time": "2016-08-20T14:39:39", 
    "glucose": 184
  }, 
  {
    "trend_arrow": "SINGLE_UP", 
    "system_time": "2016-08-20T21:33:35", 
    "display_time": "2016-08-20T14:34:30", 
    "glucose": 179
  }
]