[
  {
    "trend_arrow": "FLAT", 
    "system_time": "2016-08-09T04:34:18", 
    "display_time": "2016-08-08T21:35:13", 
    "glucose": 97
  }, 
  {
    "trend_arrow": "FLAT", 
    "system_time": "2016-08-09T04:29:19", 
    "display_time": "2016-08-08T21:30:14", 
    "glucose": 92
  }, 
  {
    "trend_arrow": "FLAT", 
    "system_time": "2016-08-09T04:24:19", 
    "display_time": "2016-08-08T21:25:15", 
    "glucose": 88
  }, 
  {
    "trend_arrow": "FLAT", 
    "system_time": "2016-08-09T04:19:17", 
    "display_time": "2016-08-08T21:20:13", 
    "glucose": 84
  }, 
  {
    "trend_arrow": "FLAT", 
    "system_time": "2016-08-09T04:14:19", 
    "display_time": "2016-08-08T21:15:14", 
    "glucose": 82
  }
]