[
  {
    "netbasalinsulin": -0.15, 
    "activity": -0.0002, 
    "basaliob": -0.001, 
    "time": "2016-08-20T17:10:39.000Z", 
    "hightempinsulin": 0, 
    "bolussnooze": 0, 
    "iob": -0.001
  }, 
  {
    "netbasalinsulin": -0.15, 
    "activity": -0.0002, 
    "basaliob": -0.001, 
    "time": "2016-08-20T17:15:39.000Z", 
    "hightempinsulin": 0, 
    "bolussnooze": 0, 
    "iob": -0.001
  }, 
  {
    "netbasalinsulin": -0.1, 
    "activity": -0.0001, 
    "basaliob": 0, 
    "time": "2016-08-20T17:20:39.000Z", 
    "hightempinsulin": 0, 
    "bolussnooze": 0, 
    "iob": 0
  }, 
  {
    "netbasalinsulin": -0.05, 
    "activity": 0, 
    "basaliob": 0, 
    "time": "2016-08-20T17:25:39.000Z", 
    "hightempinsulin": 0, 
    "bolussnooze": 0, 
    "iob": 0
  }, 
  {
    "netbasalinsulin": -0.05, 
    "activity": 0, 
    "basaliob": 0, 
    "time": "2016-08-20T17:30:39.000Z", 
    "hightempinsulin": 0, 
    "bolussnooze": 0, 
    "iob": 0
  }, 
  {
    "netbasalinsulin": 0, 
    "activity": 0, 
    "basaliob": 0, 
    "time": "2016-08-20T17:35:39.000Z", 
    "hightempinsulin": 0, 
    "bolussnooze": 0, 
    "iob": 0
  }, 
  {
    "netbasalinsulin": 0, 
    "activity": 0, 
    "basaliob": 0, 
    "time": "2016-08-20T17:40:39.000Z", 
    "hightempinsulin": 0, 
    "bolussnooze": 0, 
    "iob": 0
  }, 
  {
    "netbasalinsulin": 0, 
    "activity": 0, 
    "basaliob": 0, 
    "time": "2016-08-20T17:45:39.000Z", 
    "hightempinsulin": 0, 
    "bolussnooze": 0, 
    "iob": 0
  }, 
  {
    "netbasalinsulin": 0, 
    "activity": 0, 
    "basaliob": 0, 
    "time": "2016-08-20T17:50:39.000Z", 
    "hightempinsulin": 0, 
    "bolussnooze": 0, 
    "iob": 0
  }, 
  {
    "netbasalinsulin": 0, 
    "activity": 0, 
    "basaliob": 0, 
    "time": "2016-08-20T17:55:39.000Z", 
    "hightempinsulin": 0, 
    "bolussnooze": 0, 
    "iob": 0
  }, 
  {
    "netbasalinsulin": 0, 
    "activity": 0, 
    "basaliob": 0, 
    "time": "2016-08-20T18:00:39.000Z", 
    "hightempinsulin": 0, 
    "bolussnooze": 0, 
    "iob": 0
  }, 
  {
    "netbasalinsulin": 0, 
    "activity": 0, 
    "basaliob": 0, 
    "time": "2016-08-20T18:05:39.000Z", 
    "hightempinsulin": 0, 
    "bolussnooze": 0, 
    "iob": 0
  }, 
  {
    "netbasalinsulin": 0, 
    "activity": 0, 
    "basaliob": 0, 
    "time": "2016-08-20T18:10:39.000Z", 
    "hightempinsulin": 0, 
    "bolussnooze": 0, 
    "iob": 0
  }, 
  {
    "netbasalinsulin": 0, 
    "activity": 0, 
    "basaliob": 0, 
    "time": "2016-08-20T18:15:39.000Z", 
    "hightempinsulin": 0, 
    "bolussnooze": 0, 
    "iob": 0
  }, 
  {
    "netbasalinsulin": 0, 
    "activity": 0, 
    "basaliob": 0, 
    "time": "2016-08-20T18:20:39.000Z", 
    "hightempinsulin": 0, 
    "bolussnooze": 0, 
    "iob": 0
  }, 
  {
    "netbasalinsulin": 0, 
    "activity": 0, 
    "basaliob": 0, 
    "time": "2016-08-20T18:25:39.000Z", 
    "hightempinsulin": 0, 
    "bolussnooze": 0, 
    "iob": 0
  }, 
  {
    "netbasalinsulin": 0, 
    "activity": 0, 
    "basaliob": 0, 
    "time": "2016-08-20T18:30:39.000Z", 
    "hightempinsulin": 0, 
    "bolussnooze": 0, 
    "iob": 0
  }, 
  {
    "netbasalinsulin": 0, 
    "activity": 0, 
    "basaliob": 0, 
    "time": "2016-08-20T18:35:39.000Z", 
    "hightempinsulin": 0, 
    "bolussnooze": 0, 
    "iob": 0
  }, 
  {
    "netbasalinsulin": 0, 
    "activity": 0, 
    "basaliob": 0, 
    "time": "2016-08-20T18:40:39.000Z", 
    "hightempinsulin": 0, 
    "bolussnooze": 0, 
    "iob": 0
  }, 
  {
    "netbasalinsulin": 0, 
    "activity": 0, 
    "basaliob": 0, 
    "time": "2016-08-20T18:45:39.000Z", 
    "hightempinsulin": 0, 
    "bolussnooze": 0, 
    "iob": 0
  }, 
  {
    "netbasalinsulin": 0, 
    "activity": 0, 
    "basaliob": 0, 
    "time": "2016-08-20T18:50:39.000Z", 
    "hightempinsulin": 0, 
    "bolussnooze": 0, 
    "iob": 0
  }, 
  {
    "netbasalinsulin": 0, 
    "activity": 0, 
    "basaliob": 0, 
    "time": "2016-08-20T18:55:39.000Z", 
    "hightempinsulin": 0, 
    "bolussnooze": 0, 
    "iob": 0
  }, 
  {
    "netbasalinsulin": 0, 
    "activity": 0, 
    "basaliob": 0, 
    "time": "2016-08-20T19:00:39.000Z", 
    "hightempinsulin": 0, 
    "bolussnooze": 0, 
    "iob": 0
  }, 
  {
    "netbasalinsulin": 0, 
    "activity": 0, 
    "basaliob": 0, 
    "time": "2016-08-20T19:05:39.000Z", 
    "hightempinsulin": 0, 
    "bolussnooze": 0, 
    "iob": 0
  }, 
  {
    "netbasalinsulin": 0, 
    "activity": 0, 
    "basaliob": 0, 
    "time": "2016-08-20T19:10:39.000Z", 
    "hightempinsulin": 0, 
    "bolussnooze": 0, 
    "iob": 0
  }, 
  {
    "netbasalinsulin": 0, 
    "activity": 0, 
    "basaliob": 0, 
    "time": "2016-08-20T19:15:39.000Z", 
    "hightempinsulin": 0, 
    "bolussnooze": 0, 
    "iob": 0
  }, 
  {
    "netbasalinsulin": 0, 
    "activity": 0, 
    "basaliob": 0, 
    "time": "2016-08-20T19:20:39.000Z", 
    "hightempinsulin": 0, 
    "bolussnooze": 0, 
    "iob": 0
  }, 
  {
    "netbasalinsulin": 0, 
    "activity": 0, 
    "basaliob": 0, 
    "time": "2016-08-20T19:25:39.000Z", 
    "hightempinsulin": 0, 
    "bolussnooze": 0, 
    "iob": 0
  }, 
  {
    "netbasalinsulin": 0, 
    "activity": 0, 
    "basaliob": 0, 
    "time": "2016-08-20T19:30:39.000Z", 
    "hightempinsulin": 0, 
    "bolussnooze": 0, 
    "iob": 0
  }, 
  {
    "netbasalinsulin": 0, 
    "activity": 0, 
    "basaliob": 0, 
    "time": "2016-08-20T19:35:39.000Z", 
    "hightempinsulin": 0, 
    "bolussnooze": 0, 
    "iob": 0
  }, 
  {
    "netbasalinsulin": 0, 
    "activity": 0, 
    "basaliob": 0, 
    "time": "2016-08-20T19:40:39.000Z", 
    "hightempinsulin": 0, 
    "bolussnooze": 0, 
    "iob": 0
  }, 
  {
    "netbasalinsulin": 0, 
    "activity": 0, 
    "basaliob": 0, 
    "time": "2016-08-20T19:45:39.000Z", 
    "hightempinsulin": 0, 
    "bolussnooze": 0, 
    "iob": 0
  }, 
  {
    "netbasalinsulin": 0, 
    "activity": 0, 
    "basaliob": 0, 
    "time": "2016-08-20T19:50:39.000Z", 
    "hightempinsulin": 0, 
    "bolussnooze": 0, 
    "iob": 0
  }, 
  {
    "netbasalinsulin": 0, 
    "activity": 0, 
    "basaliob": 0, 
    "time": "2016-08-20T19:55:39.000Z", 
    "hightempinsulin": 0, 
    "bolussnooze": 0, 
    "iob": 0
  }, 
  {
    "netbasalinsulin": 0, 
    "activity": 0, 
    "basaliob": 0, 
    "time": "2016-08-20T20:00:39.000Z", 
    "hightempinsulin": 0, 
    "bolussnooze": 0, 
    "iob": 0
  }, 
  {
    "netbasalinsulin": 0, 
    "activity": 0, 
    "basaliob": 0, 
    "time": "2016-08-20T20:05:39.000Z", 
    "hightempinsulin": 0, 
    "bolussnooze": 0, 
    "iob": 0
  }, 
  {
    "netbasalinsulin": 0, 
    "activity": 0, 
    "basaliob": 0, 
    "time": "2016-08-20T20:10:39.000Z", 
    "hightempinsulin": 0, 
    "bolussnooze": 0, 
    "iob": 0
  }, 
  {
    "netbasalinsulin": 0, 
    "activity": 0, 
    "basaliob": 0, 
    "time": "2016-08-20T20:15:39.000Z", 
    "hightempinsulin": 0, 
    "bolussnooze": 0, 
    "iob": 0
  }, 
  {
    "netbasalinsulin": 0, 
    "activity": 0, 
    "basaliob": 0, 
    "time": "2016-08-20T20:20:39.000Z", 
    "hightempinsulin": 0, 
    "bolussnooze": 0, 
    "iob": 0
  }, 
  {
    "netbasalinsulin": 0, 
    "activity": 0, 
    "basaliob": 0, 
    "time": "2016-08-20T20:25:39.000Z", 
    "hightempinsulin": 0, 
    "bolussnooze": 0, 
    "iob": 0
  }, 
  {
    "netbasalinsulin": 0, 
    "activity": 0, 
    "basaliob": 0, 
    "time": "2016-08-20T20:30:39.000Z", 
    "hightempinsulin": 0, 
    "bolussnooze": 0, 
    "iob": 0
  }, 
  {
    "netbasalinsulin": 0, 
    "activity": 0, 
    "basaliob": 0, 
    "time": "2016-08-20T20:35:39.000Z", 
    "hightempinsulin": 0, 
    "bolussnooze": 0, 
    "iob": 0
  }
]